README.md
setup.cfg
setup.py
django_nameko/__init__.py
django_nameko/rpc.py
django_nameko_py3.egg-info/PKG-INFO
django_nameko_py3.egg-info/SOURCES.txt
django_nameko_py3.egg-info/dependency_links.txt
django_nameko_py3.egg-info/not-zip-safe
django_nameko_py3.egg-info/requires.txt
django_nameko_py3.egg-info/top_level.txt